README.md
setup.py
dash_id_utils/__init__.py
dash_id_utils.egg-info/PKG-INFO
dash_id_utils.egg-info/SOURCES.txt
dash_id_utils.egg-info/dependency_links.txt
dash_id_utils.egg-info/requires.txt
dash_id_utils.egg-info/top_level.txt