Metadata-Version: 2.1
Name: dash-id-utils
Version: 0.0.1
Home-page: https://github.com/pragmatic-dash/dash-id-utils
Author: mapix
Author-email: mapix.me@gmail.com
License: MIT
Classifier: Programming Language :: Python :: 3
